generate_changelog/__init__.py
generate_changelog/_attr_docs.py
generate_changelog/cli.py
generate_changelog/commits.py
generate_changelog/configuration.py
generate_changelog/context.py
generate_changelog/data_merge.py
generate_changelog/git_ops.py
generate_changelog/indented_logger.py
generate_changelog/notes.py
generate_changelog/pipeline.py
generate_changelog/release_hint.py
generate_changelog/templating.py
generate_changelog/utilities.py
generate_changelog/actions/__init__.py
generate_changelog/actions/file_processing.py
generate_changelog/actions/matching.py
generate_changelog/actions/metadata.py
generate_changelog/actions/shell.py
generate_changelog/actions/text_processing.py
generate_changelog/templates/base.md.jinja
generate_changelog/templates/commit.md.jinja
generate_changelog/templates/footer.md.jinja
generate_changelog/templates/heading.md.jinja
generate_changelog/templates/section_heading.md.jinja
generate_changelog/templates/version_heading.md.jinja
generate_changelog/templates/versions.md.jinja
generate_changelog-0.16.0.dist-info/METADATA
generate_changelog-0.16.0.dist-info/WHEEL
generate_changelog-0.16.0.dist-info/entry_points.txt
generate_changelog-0.16.0.dist-info/licenses/LICENSE
generate_changelog-0.16.0.dist-info/RECORD
