Metadata-Version: 2.4
Name: generate_changelog
Version: 0.16.0
Summary: Generate a changelog file from a local git checkout
Project-URL: Homepage, https://github.com/callowayproject/generate_changelog
Project-URL: Documentation, https://callowayproject.github.io/generate-changelog/
Project-URL: Source, https://github.com/callowayproject/generate-changelog
Author-email: Corey Oordt <coreyoordt@gmail.com>
License: MIT License
License-File: LICENSE
Keywords: change,changelog,commit,git
Classifier: Development Status :: 4 - Beta
Classifier: Environment :: Console
Classifier: Intended Audience :: Developers
Classifier: License :: OSI Approved :: MIT License
Classifier: Natural Language :: English
Classifier: Programming Language :: Python
Classifier: Programming Language :: Python :: 3.9
Classifier: Programming Language :: Python :: 3.10
Classifier: Programming Language :: Python :: 3.11
Classifier: Programming Language :: Python :: 3.12
Classifier: Programming Language :: Python :: 3.13
Classifier: Topic :: Software Development
Classifier: Topic :: Software Development :: Build Tools
Classifier: Topic :: Software Development :: Version Control :: Git
Requires-Python: >=3.9
Requires-Dist: click>=8.1.7
Requires-Dist: gitpython
Requires-Dist: jinja2
Requires-Dist: mdformat>=0.7.22
Requires-Dist: more-itertools
Requires-Dist: rich-click>=1.8.4
Requires-Dist: ruamel-yaml
Requires-Dist: typing-extensions; python_version < '3.10'
